taps/__init__.py
taps/attribute_format.py
taps/config.py
taps/json_fetch.py
taps/pacman.py
taps/taps.conf
taps/text_format.py
taps-1.1.0.data/scripts/taps
taps-1.1.0.dist-info/LICENSE
taps-1.1.0.dist-info/METADATA
taps-1.1.0.dist-info/WHEEL
taps-1.1.0.dist-info/top_level.txt
taps-1.1.0.dist-info/RECORD
