Metadata-Version: 2.1
Name: taps
Version: 1.1.0
Summary: True Arch package security - audit and query packages
Home-page: https://github.com/Vimru/taps
License: GPLv3
Platform: UNKNOWN
Classifier: Programming Language :: Python :: 3
Classifier: License :: OSI Approved :: GNU General Public License v3 (GPLv3)
Requires-Python: >=3.6
Requires-Dist: colorful
Requires-Dist: setuptools
Requires-Dist: requests
Requires-Dist: pyalpm
